CHANGELOG.md
LICENSE
dropship/__init__.py
dropship/constant.py
dropship/dropship.py
dropship/transfer.py
dropship/ui/dropship.css
dropship/ui/dropship.ui
dropship/ui/pendingTransferRow.ui
dropship/ui_templates.py
dropship/wormhole.py
dropship-0.0.5.dist-info/entry_points.txt
dropship-0.0.5.dist-info/LICENSE
dropship-0.0.5.dist-info/WHEEL
dropship-0.0.5.dist-info/METADATA
dropship-0.0.5.dist-info/RECORD
