Metadata-Version: 2.1
Name: dropship
Version: 0.0.5
Summary: Magic wormhole with a nice graphical interface
Home-page: https://git.vvvvvvaria.org/rra/dropship
License: GPLv3
Keywords: magic-wormhole,gtk,pygobject
Author: decentral1se
Author-email: hi@decentral1.se
Requires-Python: >=3.6,<4.0
Classifier: License :: Other/Proprietary License
Classifier: Programming Language :: Python :: 3
Classifier: Programming Language :: Python :: 3.6
Classifier: Programming Language :: Python :: 3.7
Classifier: Programming Language :: Python :: 3.8
Classifier: Programming Language :: Python :: 3.9
Requires-Dist: magic-wormhole (>=0.12.0,<0.13.0)
Requires-Dist: pycairo (<1.20)
Requires-Dist: pygobject (<3.32)
Requires-Dist: trio (>=0.17.0,<0.18.0)
Requires-Dist: trio-gtk (>=3.0.0,<4.0.0)
Project-URL: Repository, https://git.vvvvvvaria.org/rra/dropship
